wade/__init__.py
wade/wade.py
wade-0.0.1.dev3.dist-info/METADATA
wade-0.0.1.dev3.dist-info/RECORD
wade-0.0.1.dev3.dist-info/WHEEL
wade-0.0.1.dev3.dist-info/entry_points.txt
wade-0.0.1.dev3.dist-info/top_level.txt
